grizzly_cli/__init__.py
grizzly_cli/__main__.py
grizzly_cli/__version__.py
grizzly_cli/auth.py
grizzly_cli/init.py
grizzly_cli/keyvault.py
grizzly_cli/local.py
grizzly_cli/py.typed
grizzly_cli/run.py
grizzly_cli/argparse/__init__.py
grizzly_cli/argparse/markdown.py
grizzly_cli/argparse/bashcompletion/__init__.py
grizzly_cli/argparse/bashcompletion/bashcompletion.bash
grizzly_cli/argparse/bashcompletion/types.py
grizzly_cli/distributed/__init__.py
grizzly_cli/distributed/build.py
grizzly_cli/distributed/clean.py
grizzly_cli/static/Containerfile
grizzly_cli/static/compose.yaml
grizzly_cli/utils/__init__.py
grizzly_cli/utils/configuration.py
grizzly_loadtester_cli-3.2.28.dist-info/METADATA
grizzly_loadtester_cli-3.2.28.dist-info/WHEEL
grizzly_loadtester_cli-3.2.28.dist-info/entry_points.txt
grizzly_loadtester_cli-3.2.28.dist-info/RECORD
