Metadata-Version: 2.4
Name: grizzly-loadtester-cli
Version: 3.2.28
Summary: Command line interface for grizzly-loadtester
Project-URL: Documentation, https://biometria-se.github.io/grizzly/command-line-interface/usage/
Project-URL: Code, https://github.com/biometria-se/grizzly/
Project-URL: Tracker, https://github.com/Biometria-se/grizzly/issues
Author-email: biometria <opensource@biometria.se>
Maintainer-email: Mikael Göransson <github@mgor.se>
License-Expression: MIT
Keywords: behave,cli,command line interface,grizzly,grizzly-loadtester,load,loadtest,locust,performance,traffic generator
Classifier: Development Status :: 5 - Production/Stable
Classifier: License :: OSI Approved :: MIT License
Classifier: Natural Language :: English
Classifier: Programming Language :: Python
Classifier: Programming Language :: Python :: 3 :: Only
Classifier: Programming Language :: Python :: 3.10
Classifier: Programming Language :: Python :: 3.11
Classifier: Programming Language :: Python :: 3.12
Classifier: Programming Language :: Python :: 3.13
Classifier: Programming Language :: Python :: Implementation :: CPython
Requires-Python: >=3.10
Requires-Dist: azure-identity>=1.24.0
Requires-Dist: azure-keyvault-secrets>=4.10.0
Requires-Dist: grizzly-loadtester-common
Requires-Dist: progress>=1.6.1
Requires-Dist: requests>=2.32.5
Requires-Dist: tomli>=2.2.1
